deformation_inversion_layer/__init__.py
deformation_inversion_layer/fixed_point_invert_deformation.py
deformation_inversion_layer/fixed_point_iteration.py
deformation_inversion_layer/interface.py
deformation_inversion_layer/py.typed
deformation_inversion_layer/interpolator/__init__.py
deformation_inversion_layer/interpolator/algorithm.py
deformation_inversion_layer/interpolator/wrapper.py
deformation_inversion_layer-1.1.2.dist-info/LICENSE
deformation_inversion_layer-1.1.2.dist-info/METADATA
deformation_inversion_layer-1.1.2.dist-info/WHEEL
deformation_inversion_layer-1.1.2.dist-info/top_level.txt
deformation_inversion_layer-1.1.2.dist-info/RECORD
