Metadata-Version: 2.1
Name: deformation-inversion-layer
Version: 1.1.2
Summary: Deformation inversion layer is a neural network layer for inverting deformation fields
Author: Joel Honkamaa
License: MIT License
Project-URL: Homepage, https://github.com/honkamj/deformation-inversion-layer
Keywords: deep learning,neural networks,fixed point iteration,deep equilibrium networks,image registration,deformation,coordinate mapping,pytorch
Classifier: Programming Language :: Python :: 3
Classifier: License :: OSI Approved :: MIT License
Classifier: Operating System :: OS Independent
Requires-Python: >=3.8
License-File: LICENSE
Requires-Dist: torch >=1.10
